ppio_sandbox/__init__.py
ppio_sandbox/code_interpreter/__init__.py
ppio_sandbox/code_interpreter/charts.py
ppio_sandbox/code_interpreter/code_interpreter_async.py
ppio_sandbox/code_interpreter/code_interpreter_sync.py
ppio_sandbox/code_interpreter/constants.py
ppio_sandbox/code_interpreter/exceptions.py
ppio_sandbox/code_interpreter/models.py
ppio_sandbox/code_interpreter/tests/benchmarking.py
ppio_sandbox/code_interpreter/tests/conftest.py
ppio_sandbox/code_interpreter/tests/async/test_async_bash.py
ppio_sandbox/code_interpreter/tests/async/test_async_basic.py
ppio_sandbox/code_interpreter/tests/async/test_async_callbacks.py
ppio_sandbox/code_interpreter/tests/async/test_async_custom_repr_object.py
ppio_sandbox/code_interpreter/tests/async/test_async_data.py
ppio_sandbox/code_interpreter/tests/async/test_async_default_kernels.py
ppio_sandbox/code_interpreter/tests/async/test_async_display_data.py
ppio_sandbox/code_interpreter/tests/async/test_async_execution_count.py
ppio_sandbox/code_interpreter/tests/async/test_async_kernels.py
ppio_sandbox/code_interpreter/tests/async/test_async_reconnect.py
ppio_sandbox/code_interpreter/tests/async/test_async_statefulness.py
ppio_sandbox/code_interpreter/tests/async/test_async_streaming.py
ppio_sandbox/code_interpreter/tests/async/env_vars/test_bash.py
ppio_sandbox/code_interpreter/tests/async/env_vars/test_java.py
ppio_sandbox/code_interpreter/tests/async/env_vars/test_js.py
ppio_sandbox/code_interpreter/tests/async/env_vars/test_python.py
ppio_sandbox/code_interpreter/tests/async/env_vars/test_r.py
ppio_sandbox/code_interpreter/tests/charts/test_bar.py
ppio_sandbox/code_interpreter/tests/charts/test_box_and_whiskers.py
ppio_sandbox/code_interpreter/tests/charts/test_json.py
ppio_sandbox/code_interpreter/tests/charts/test_line.py
ppio_sandbox/code_interpreter/tests/charts/test_log_chart.py
ppio_sandbox/code_interpreter/tests/charts/test_pie.py
ppio_sandbox/code_interpreter/tests/charts/test_scale.py
ppio_sandbox-1.0.4.dist-info/METADATA
ppio_sandbox-1.0.4.dist-info/WHEEL
ppio_sandbox-1.0.4.dist-info/RECORD
