Metadata-Version: 2.4
Name: ppio-sandbox
Version: 1.0.4
Summary: PPIO Sandbox SDK - Python library for PPIO Agent Sandbox
Project-URL: Homepage, https://ppio.com/
Project-URL: Documentation, https://ppio-sandbox-sdk-python.readthedocs.io/
Project-URL: Repository, https://github.com/ppio/ppio-sandbox-sdk-python
Project-URL: Bug Tracker, https://github.com/ppio/ppio-sandbox-sdk-python/issues
Project-URL: Changelog, https://github.com/ppio/ppio-sandbox-sdk-python/blob/main/CHANGELOG.md
Author-email: PPIO <viktor@pplabs.org>
Maintainer-email: PPIO <viktor@pplabs.org>
License: MIT
Keywords: agent,ai,code-interpreter,desktop-automation,ppio,sandbox,sdk
Classifier: Development Status :: 4 - Beta
Classifier: Intended Audience :: Developers
Classifier: License :: OSI Approved :: MIT License
Classifier: Operating System :: OS Independent
Classifier: Programming Language :: Python :: 3
Classifier: Programming Language :: Python :: 3.9
Classifier: Programming Language :: Python :: 3.10
Classifier: Programming Language :: Python :: 3.11
Classifier: Programming Language :: Python :: 3.12
Classifier: Topic :: Scientific/Engineering :: Artificial Intelligence
Classifier: Topic :: Software Development :: Libraries :: Python Modules
Classifier: Topic :: System :: Operating System
Requires-Python: >=3.9
Requires-Dist: attrs>=23.2.0
Requires-Dist: httpcore>=1.0.5
Requires-Dist: httpx<1.0.0,>=0.27.0
Requires-Dist: packaging>=24.1
Requires-Dist: protobuf>=4.21.0
Requires-Dist: python-dateutil>=2.8.2
Requires-Dist: typing-extensions>=4.1.0
Provides-Extra: all
Requires-Dist: matplotlib>=3.6.0; extra == 'all'
Requires-Dist: numpy>=1.21.0; extra == 'all'
Requires-Dist: opencv-python>=4.7.0; extra == 'all'
Requires-Dist: pandas>=1.5.0; extra == 'all'
Requires-Dist: pillow>=9.0.0; extra == 'all'
Requires-Dist: plotly>=5.0.0; extra == 'all'
Requires-Dist: pyautogui>=0.9.54; extra == 'all'
Requires-Dist: pynput>=1.7.6; extra == 'all'
Requires-Dist: python-dateutil>=2.8.2; extra == 'all'
